MANIFEST.in
setup.py
prompt2/__init__.py
prompt2/backend.py
prompt2/cli.py
prompt2/exception.py
prompt2/jinja2.py
prompt2/model.py
prompt2/parser.py
prompt2/prompt.py
prompt2/pytest.py
prompt2.egg-info/PKG-INFO
prompt2.egg-info/SOURCES.txt
prompt2.egg-info/dependency_links.txt
prompt2.egg-info/entry_points.txt
prompt2.egg-info/requires.txt
prompt2.egg-info/top_level.txt
prompt2/backends/__init__.py
prompt2/backends/litellm.py