Metadata-Version: 2.2
Name: prompt2
Version: 5.2.3
Home-page: https://yourlabs.io/oss/cli2
Author: James Pic
Author-email: jamespic@gmail.com
License: MIT
Keywords: cli
Requires-Python: >=3.6
Requires-Dist: cli2
Requires-Dist: markdown-it-py
Requires-Dist: jinja2
Dynamic: author
Dynamic: author-email
Dynamic: home-page
Dynamic: keywords
Dynamic: license
Dynamic: requires-dist
Dynamic: requires-python
